pynetcheck/__init__.py
pynetcheck/archive/output_1713283371.388187.json
pynetcheck/archive/output_1713287098.9189737.json
pynetcheck/archive/output_1713287258.6043513.json
pynetcheck/archive/output_1713287738.6383476.json
pynetcheck/archive/output_1713291137.528805.json
pynetcheck/archive/output_1713291437.5512764.json
pynetcheck/models/__init__.py
pynetcheck/models/device.py
pynetcheck/models/shared.py
pynetcheck/pytest.ini
pynetcheck/tests/__init__.py
pynetcheck/tests/cisco/__init__.py
pynetcheck/tests/cisco/conftest.py
pynetcheck/tests/cisco/test_servers.py
pynetcheck/tests/conftest.py
pynetcheck/tests/cve/__init__.py
pynetcheck/tests/cve/cisco/__init__.py
pynetcheck/tests/cve/cisco/test_cve_2023_20198_ios_xe.py
pynetcheck/tests/cve/cisco/test_cve_2024_20278.py
pynetcheck/tests/cve/paloalto/__init__.py
pynetcheck/tests/cve/paloalto/test_cve_2024_3400.py
pynetcheck/tests/paloalto/__init__.py
pynetcheck/tests/paloalto/conftest.py
pynetcheck-1.0.2.dist-info/entry_points.txt
pynetcheck-1.0.2.dist-info/LICENSE
pynetcheck-1.0.2.dist-info/METADATA
pynetcheck-1.0.2.dist-info/WHEEL
pynetcheck-1.0.2.dist-info/RECORD
