Metadata-Version: 2.1
Name: PyNetCheck
Version: 1.0.2
Summary: Python Network device checker using Pytest and IP Fabric.
Home-page: https://gitlab.com/ip-fabric/integrations/pynetcheck
License: MIT
Keywords: ipfabric,ip-fabric,community-fabric
Author: Solution Architecture
Author-email: solution.architecture@ipfabric.io
Requires-Python: >=3.8.1,<4.0.0
Classifier: License :: OSI Approved :: MIT License
Classifier: Programming Language :: Python :: 3
Classifier: Programming Language :: Python :: 3.9
Classifier: Programming Language :: Python :: 3.10
Classifier: Programming Language :: Python :: 3.11
Classifier: Programming Language :: Python :: 3.12
Requires-Dist: ciscoconfparse (>=1.9.0,<2.0.0)
Requires-Dist: ipfabric (>=6.7.0,<7.0.0)
Requires-Dist: netutils (>=1.8.0,<2.0.0)
Requires-Dist: pytest (>=8.0.0,<9.0.0)
Requires-Dist: pytest-html-reporter (>=0.2.9,<0.3.0)
Project-URL: Changelog, https://gitlab.com/ip-fabric/integrations/pynetcheck/-/blob/main/CHANGELOG.md
Project-URL: Documentation, https://gitlab.com/ip-fabric/integrations/pynetcheck
Project-URL: IP Fabric, https://ipfabric.io/
Project-URL: Repository, https://gitlab.com/ip-fabric/integrations/pynetcheck
